tabs.py
tabs_buoys-2.5.dist-info/METADATA
tabs_buoys-2.5.dist-info/WHEEL
tabs_buoys-2.5.dist-info/top_level.txt
tabs_buoys-2.5.dist-info/RECORD
